{"sid":"df51c8d4f2f282e373452d7d44845d3a484c6a0fb5027030ef3615494ce0a8d17cf6f81c","prism_version":"1.0.9","prism_wnum":112,"prism_wordsInfo":[{"word":"检验报告单","pos":[{"x":338,"y":46},{"x":469,"y":46},{"x":469,"y":63},{"x":338,"y":63}],"direction":0},{"word":"妇","pos":[{"x":63,"y":82},{"x":76,"y":82},{"x":76,"y":95},{"x":63,"y":95}],"direction":0},{"word":"送检医师：","pos":[{"x":380,"y":82},{"x":439,"y":82},{"x":439,"y":93},{"x":380,"y":93}],"direction":0},{"word":"样本编号：84","pos":[{"x":523,"y":85},{"x":606,"y":87},{"x":606,"y":99},{"x":523,"y":97}],"direction":0},{"word":"性","pos":[{"x":61,"y":98},{"x":77,"y":98},{"x":77,"y":113},{"x":61,"y":113}],"direction":0},{"word":"标本状况：正常","pos":[{"x":380,"y":101},{"x":474,"y":103},{"x":474,"y":115},{"x":380,"y":113}],"direction":0},{"word":"标木种类：血清","pos":[{"x":523,"y":104},{"x":616,"y":106},{"x":615,"y":119},{"x":522,"y":116}],"direction":0},{"word":"年","pos":[{"x":59,"y":116},{"x":77,"y":116},{"x":77,"y":131},{"x":59,"y":131}],"direction":0},{"word":"龄：53岁","pos":[{"x":98,"y":119},{"x":152,"y":119},{"x":152,"y":130},{"x":98,"y":130}],"direction":0},{"word":"病床号：","pos":[{"x":207,"y":118},{"x":270,"y":118},{"x":270,"y":130},{"x":207,"y":130}],"direction":0},{"word":"临床诊断：","pos":[{"x":381,"y":121},{"x":440,"y":121},{"x":440,"y":132},{"x":381,"y":132}],"direction":0},{"word":"序号","pos":[{"x":56,"y":148},{"x":82,"y":148},{"x":82,"y":158},{"x":56,"y":158}],"direction":0},{"word":"中文名称","pos":[{"x":90,"y":147},{"x":145,"y":147},{"x":145,"y":158},{"x":90,"y":158}],"direction":0},{"word":"英文名称","pos":[{"x":224,"y":147},{"x":279,"y":147},{"x":279,"y":158},{"x":224,"y":158}],"direction":0},{"word":"结果","pos":[{"x":313,"y":148},{"x":342,"y":148},{"x":342,"y":159},{"x":313,"y":159}],"direction":0},{"word":"状态","pos":[{"x":385,"y":149},{"x":413,"y":149},{"x":413,"y":159},{"x":385,"y":159}],"direction":0},{"word":"单位","pos":[{"x":447,"y":150},{"x":474,"y":150},{"x":474,"y":160},{"x":447,"y":160}],"direction":0},{"word":"参考值","pos":[{"x":537,"y":151},{"x":576,"y":151},{"x":576,"y":162},{"x":537,"y":162}],"direction":0},{"word":"总阻红素","pos":[{"x":90,"y":167},{"x":139,"y":167},{"x":139,"y":177},{"x":90,"y":177}],"direction":0},{"word":"TBi 1","pos":[{"x":233,"y":169},{"x":261,"y":169},{"x":261,"y":178},{"x":233,"y":178}],"direction":0},{"word":"51.8","pos":[{"x":312,"y":169},{"x":343,"y":169},{"x":343,"y":179},{"x":312,"y":179}],"direction":0},{"word":"umol/Le","pos":[{"x":440,"y":170},{"x":485,"y":170},{"x":485,"y":181},{"x":440,"y":181}],"direction":0},{"word":"17.1","pos":[{"x":534,"y":172},{"x":567,"y":172},{"x":567,"y":181},{"x":534,"y":181}],"direction":0},{"word":"2","pos":[{"x":57,"y":184},{"x":72,"y":184},{"x":72,"y":196},{"x":57,"y":196}],"direction":0},{"word":"直接胆红素","pos":[{"x":90,"y":185},{"x":152,"y":185},{"x":152,"y":195},{"x":90,"y":195}],"direction":0},{"word":"DBi 1","pos":[{"x":232,"y":186},{"x":261,"y":186},{"x":261,"y":195},{"x":232,"y":195}],"direction":0},{"word":"47.2","pos":[{"x":313,"y":186},{"x":343,"y":186},{"x":343,"y":196},{"x":313,"y":196}],"direction":0},{"word":"umol/L","pos":[{"x":440,"y":189},{"x":484,"y":187},{"x":485,"y":197},{"x":441,"y":199}],"direction":0},{"word":"45.13","pos":[{"x":533,"y":189},{"x":567,"y":189},{"x":567,"y":198},{"x":533,"y":198}],"direction":0},{"word":"3","pos":[{"x":58,"y":201},{"x":73,"y":201},{"x":73,"y":214},{"x":58,"y":214}],"direction":0},{"word":"何接胆红素","pos":[{"x":90,"y":203},{"x":152,"y":203},{"x":152,"y":213},{"x":90,"y":213}],"direction":0},{"word":"1Bi1","pos":[{"x":233,"y":204},{"x":261,"y":204},{"x":261,"y":214},{"x":233,"y":214}],"direction":0},{"word":"46","pos":[{"x":313,"y":205},{"x":335,"y":205},{"x":335,"y":214},{"x":313,"y":214}],"direction":0},{"word":"umo 1/L","pos":[{"x":440,"y":207},{"x":484,"y":205},{"x":485,"y":215},{"x":441,"y":217}],"direction":0},{"word":"0.5-10.5","pos":[{"x":532,"y":206},{"x":586,"y":206},{"x":586,"y":216},{"x":532,"y":216}],"direction":0},{"word":"4","pos":[{"x":60,"y":221},{"x":71,"y":221},{"x":71,"y":230},{"x":60,"y":230}],"direction":0},{"word":"总蛋白","pos":[{"x":92,"y":220},{"x":128,"y":220},{"x":128,"y":230},{"x":92,"y":230}],"direction":0},{"word":"TP","pos":[{"x":233,"y":221},{"x":250,"y":221},{"x":250,"y":233},{"x":233,"y":233}],"direction":0},{"word":"80.0","pos":[{"x":313,"y":223},{"x":342,"y":223},{"x":342,"y":232},{"x":313,"y":232}],"direction":0},{"word":"8/L","pos":[{"x":439,"y":225},{"x":464,"y":222},{"x":465,"y":233},{"x":440,"y":235}],"direction":0},{"word":"66-87","pos":[{"x":532,"y":224},{"x":566,"y":224},{"x":566,"y":233},{"x":532,"y":233}],"direction":0},{"word":"5","pos":[{"x":61,"y":237},{"x":72,"y":237},{"x":72,"y":248},{"x":61,"y":248}],"direction":0},{"word":"白蛋白","pos":[{"x":92,"y":238},{"x":128,"y":238},{"x":128,"y":248},{"x":92,"y":248}],"direction":0},{"word":"ALB","pos":[{"x":232,"y":240},{"x":257,"y":240},{"x":257,"y":250},{"x":232,"y":250}],"direction":0},{"word":"37.7","pos":[{"x":312,"y":241},{"x":342,"y":241},{"x":342,"y":250},{"x":312,"y":250}],"direction":0},{"word":"g/L","pos":[{"x":439,"y":243},{"x":464,"y":240},{"x":465,"y":251},{"x":440,"y":253}],"direction":0},{"word":"32-52","pos":[{"x":532,"y":241},{"x":566,"y":241},{"x":566,"y":251},{"x":532,"y":251}],"direction":0},{"word":"6","pos":[{"x":60,"y":256},{"x":74,"y":256},{"x":74,"y":266},{"x":60,"y":266}],"direction":0},{"word":"球货白","pos":[{"x":92,"y":256},{"x":130,"y":256},{"x":130,"y":266},{"x":92,"y":266}],"direction":0},{"word":"GL0","pos":[{"x":233,"y":258},{"x":256,"y":258},{"x":256,"y":267},{"x":233,"y":267}],"direction":0},{"word":"42.3","pos":[{"x":313,"y":258},{"x":342,"y":258},{"x":342,"y":268},{"x":313,"y":268}],"direction":0},{"word":"君/L","pos":[{"x":440,"y":259},{"x":463,"y":259},{"x":463,"y":270},{"x":440,"y":270}],"direction":0},{"word":"19-34","pos":[{"x":532,"y":259},{"x":566,"y":259},{"x":566,"y":268},{"x":532,"y":268}],"direction":0},{"word":"7","pos":[{"x":63,"y":272},{"x":73,"y":272},{"x":73,"y":282},{"x":63,"y":282}],"direction":0},{"word":"白/球蛋白比","pos":[{"x":94,"y":272},{"x":160,"y":273},{"x":160,"y":285},{"x":94,"y":283}],"direction":0},{"word":"A/G","pos":[{"x":233,"y":276},{"x":257,"y":276},{"x":257,"y":285},{"x":233,"y":285}],"direction":0},{"word":"0.89","pos":[{"x":312,"y":276},{"x":342,"y":276},{"x":342,"y":286},{"x":312,"y":286}],"direction":0},{"word":"1.2-2.5","pos":[{"x":531,"y":276},{"x":579,"y":276},{"x":579,"y":286},{"x":531,"y":286}],"direction":0},{"word":"8","pos":[{"x":63,"y":289},{"x":79,"y":289},{"x":79,"y":300},{"x":63,"y":300}],"direction":0},{"word":"前白蛋白","pos":[{"x":95,"y":290},{"x":143,"y":290},{"x":143,"y":300},{"x":95,"y":300}],"direction":0},{"word":"PA","pos":[{"x":233,"y":293},{"x":251,"y":293},{"x":251,"y":302},{"x":233,"y":302}],"direction":0},{"word":"0.13","pos":[{"x":312,"y":294},{"x":341,"y":294},{"x":341,"y":304},{"x":312,"y":304}],"direction":0},{"word":"g/L","pos":[{"x":440,"y":294},{"x":462,"y":294},{"x":462,"y":304},{"x":440,"y":304}],"direction":0},{"word":"0.2-0.4","pos":[{"x":529,"y":294},{"x":577,"y":294},{"x":577,"y":303},{"x":529,"y":303}],"direction":0},{"word":"9","pos":[{"x":66,"y":305},{"x":78,"y":305},{"x":78,"y":316},{"x":66,"y":316}],"direction":0},{"word":"两发酸氨基转移酶","pos":[{"x":96,"y":306},{"x":191,"y":308},{"x":191,"y":319},{"x":96,"y":317}],"direction":0},{"word":"ALT","pos":[{"x":234,"y":311},{"x":256,"y":311},{"x":256,"y":320},{"x":234,"y":320}],"direction":0},{"word":"98","pos":[{"x":312,"y":312},{"x":329,"y":312},{"x":329,"y":321},{"x":312,"y":321}],"direction":0},{"word":"IU/L","pos":[{"x":440,"y":312},{"x":468,"y":312},{"x":468,"y":321},{"x":440,"y":321}],"direction":0},{"word":"K50","pos":[{"x":530,"y":312},{"x":552,"y":312},{"x":552,"y":321},{"x":530,"y":321}],"direction":0},{"word":"10","pos":[{"x":67,"y":323},{"x":85,"y":323},{"x":85,"y":335},{"x":67,"y":335}],"direction":0},{"word":"天冬氨装氨基转移裤","pos":[{"x":97,"y":323},{"x":204,"y":326},{"x":204,"y":338},{"x":96,"y":334}],"direction":0},{"word":"AST","pos":[{"x":234,"y":329},{"x":256,"y":327},{"x":257,"y":337},{"x":235,"y":339}],"direction":0},{"word":"90","pos":[{"x":312,"y":329},{"x":328,"y":329},{"x":328,"y":338},{"x":312,"y":338}],"direction":0},{"word":"IU/L","pos":[{"x":440,"y":330},{"x":468,"y":330},{"x":468,"y":339},{"x":440,"y":339}],"direction":0},{"word":"(55","pos":[{"x":530,"y":329},{"x":551,"y":329},{"x":551,"y":338},{"x":530,"y":338}],"direction":0},{"word":"1Y","pos":[{"x":70,"y":339},{"x":84,"y":339},{"x":84,"y":351},{"x":70,"y":351}],"direction":0},{"word":"被性磷截酶","pos":[{"x":97,"y":339},{"x":159,"y":343},{"x":158,"y":353},{"x":96,"y":350}],"direction":0},{"word":"ALP","pos":[{"x":233,"y":346},{"x":257,"y":344},{"x":258,"y":354},{"x":234,"y":356}],"direction":0},{"word":"476","pos":[{"x":312,"y":346},{"x":335,"y":346},{"x":335,"y":356},{"x":312,"y":356}],"direction":0},{"word":"10/L","pos":[{"x":440,"y":346},{"x":468,"y":346},{"x":468,"y":355},{"x":440,"y":355}],"direction":0},{"word":"40-130","pos":[{"x":529,"y":345},{"x":570,"y":345},{"x":570,"y":355},{"x":529,"y":355}],"direction":0},{"word":"12","pos":[{"x":70,"y":356},{"x":88,"y":356},{"x":88,"y":368},{"x":70,"y":368}],"direction":0},{"word":"乳酸膜氢面","pos":[{"x":99,"y":358},{"x":159,"y":358},{"x":159,"y":368},{"x":99,"y":368}],"direction":0},{"word":"LDH","pos":[{"x":235,"y":362},{"x":259,"y":362},{"x":259,"y":371},{"x":235,"y":371}],"direction":0},{"word":"167","pos":[{"x":312,"y":363},{"x":335,"y":363},{"x":335,"y":372},{"x":312,"y":372}],"direction":0},{"word":"1U/L","pos":[{"x":439,"y":363},{"x":466,"y":363},{"x":466,"y":372},{"x":439,"y":372}],"direction":0},{"word":"250","pos":[{"x":528,"y":362},{"x":556,"y":362},{"x":556,"y":371},{"x":528,"y":371}],"direction":0},{"word":"13","pos":[{"x":72,"y":371},{"x":88,"y":371},{"x":88,"y":384},{"x":72,"y":384}],"direction":0},{"word":"谷氨酰转肚","pos":[{"x":101,"y":372},{"x":171,"y":374},{"x":171,"y":385},{"x":101,"y":383}],"direction":0},{"word":"GGT","pos":[{"x":236,"y":378},{"x":257,"y":378},{"x":257,"y":387},{"x":236,"y":387}],"direction":0},{"word":"498","pos":[{"x":313,"y":379},{"x":335,"y":379},{"x":335,"y":388},{"x":313,"y":388}],"direction":0},{"word":"IU/L","pos":[{"x":438,"y":379},{"x":465,"y":379},{"x":465,"y":388},{"x":438,"y":388}],"direction":0},{"word":"8-61","pos":[{"x":526,"y":378},{"x":553,"y":378},{"x":553,"y":387},{"x":526,"y":387}],"direction":0},{"word":"14","pos":[{"x":74,"y":387},{"x":90,"y":387},{"x":90,"y":400},{"x":74,"y":400}],"direction":0},{"word":"A岩糖苷销","pos":[{"x":105,"y":388},{"x":190,"y":391},{"x":189,"y":402},{"x":104,"y":399}],"direction":0},{"word":"AFU","pos":[{"x":237,"y":394},{"x":259,"y":394},{"x":259,"y":403},{"x":237,"y":403}],"direction":0},{"word":"63","pos":[{"x":312,"y":395},{"x":328,"y":395},{"x":328,"y":403},{"x":312,"y":403}],"direction":0},{"word":"IL/E","pos":[{"x":438,"y":394},{"x":464,"y":394},{"x":464,"y":404},{"x":438,"y":404}],"direction":0},{"word":"10-35","pos":[{"x":526,"y":394},{"x":559,"y":394},{"x":559,"y":403},{"x":526,"y":403}],"direction":0},{"word":"15","pos":[{"x":76,"y":401},{"x":93,"y":401},{"x":93,"y":415},{"x":76,"y":415}],"direction":0},{"word":"总","pos":[{"x":104,"y":402},{"x":152,"y":405},{"x":151,"y":416},{"x":103,"y":413}],"direction":0},{"word":"TBA","pos":[{"x":238,"y":409},{"x":259,"y":409},{"x":259,"y":418},{"x":238,"y":418}],"direction":0},{"word":"97.5","pos":[{"x":312,"y":409},{"x":342,"y":410},{"x":341,"y":421},{"x":311,"y":419}],"direction":0},{"word":"umo 1/L","pos":[{"x":435,"y":410},{"x":476,"y":410},{"x":476,"y":419},{"x":435,"y":419}],"direction":0},{"word":"15","pos":[{"x":524,"y":409},{"x":546,"y":409},{"x":546,"y":419},{"x":524,"y":419}],"direction":0},{"word":"16","pos":[{"x":77,"y":415},{"x":94,"y":415},{"x":94,"y":429},{"x":77,"y":429}],"direction":0},{"word":"职简","pos":[{"x":104,"y":417},{"x":153,"y":420},{"x":152,"y":431},{"x":103,"y":428}],"direction":0},{"word":"CHE","pos":[{"x":238,"y":424},{"x":261,"y":424},{"x":261,"y":433},{"x":238,"y":433}],"direction":0},{"word":"5817","pos":[{"x":312,"y":425},{"x":340,"y":425},{"x":340,"y":434},{"x":312,"y":434}],"direction":0},{"word":"IU/L","pos":[{"x":435,"y":426},{"x":462,"y":426},{"x":462,"y":435},{"x":435,"y":435}],"direction":0},{"word":"5320-12920","pos":[{"x":523,"y":425},{"x":588,"y":425},{"x":588,"y":435},{"x":523,"y":435}],"direction":0}],"height":525,"width":700,"orgHeight":525,"orgWidth":700,"content":"检验报告单 妇 送检医师： 样本编号：84 性 标本状况：正常 标木种类：血清 年 龄：53岁 病床号： 临床诊断： 序号 中文名称 英文名称 结果 状态 单位 参考值 总阻红素 TBi 1 51.8 umol/Le 17.1 2 直接胆红素 DBi 1 47.2 umol/L 45.13 3 何接胆红素 1Bi1 46 umo 1/L 0.5-10.5 4 总蛋白 TP 80.0 8/L 66-87 5 白蛋白 ALB 37.7 g/L 32-52 6 球货白 GL0 42.3 君/L 19-34 7 白/球蛋白比 A/G 0.89 1.2-2.5 8 前白蛋白 PA 0.13 g/L 0.2-0.4 9 两发酸氨基转移酶 ALT 98 IU/L K50 10 天冬氨装氨基转移裤 AST 90 IU/L (55 1Y 被性磷截酶 ALP 476 10/L 40-130 12 乳酸膜氢面 LDH 167 1U/L 250 13 谷氨酰转肚 GGT 498 IU/L 8-61 14 A岩糖苷销 AFU 63 IL/E 10-35 15 总 TBA 97.5 umo 1/L 15 16 职简 CHE 5817 IU/L 5320-12920 "}
