{"TextDetections":[{"DetectedText":"安钢职工总医院检验报告单","Confidence":99,"Polygon":[{"X":269,"Y":33},{"X":269,"Y":61},{"X":571,"Y":60},{"X":571,"Y":32}],"AdvancedInfo":"{\"Parag\":{\"ParagNo\":1}}"},{"DetectedText":"粘\\姓名:.","Confidence":87,"Polygon":[{"X":21,"Y":81},{"X":24,"Y":64},{"X":116,"Y":77},{"X":113,"Y":95}],"AdvancedInfo":"{\"Parag\":{\"ParagNo\":2}}"},{"DetectedText":"患者编号:","Confidence":99,"Polygon":[{"X":213,"Y":71},{"X":213,"Y":88},{"X":278,"Y":88},{"X":278,"Y":71}],"AdvancedInfo":"{\"Parag\":{\"ParagNo\":3}}"},{"DetectedText":"标本号:11","Confidence":99,"Polygon":[{"X":412,"Y":72},{"X":412,"Y":89},{"X":499,"Y":88},{"X":498,"Y":71}],"AdvancedInfo":"{\"Parag\":{\"ParagNo\":4}}"},{"DetectedText":"送检时间:2018/11/23 9:30","Confidence":94,"Polygon":[{"X":573,"Y":88},{"X":573,"Y":71},{"X":765,"Y":71},{"X":765,"Y":88}],"AdvancedInfo":"{\"Parag\":{\"ParagNo\":5}}"},{"DetectedText":"贴","Confidence":98,"Polygon":[{"X":23,"Y":102},{"X":23,"Y":119},{"X":42,"Y":119},{"X":42,"Y":102}],"AdvancedInfo":"{\"Parag\":{\"ParagNo\":6}}"},{"DetectedText":"1性别:男","Confidence":92,"Polygon":[{"X":49,"Y":109},{"X":49,"Y":92},{"X":127,"Y":94},{"X":126,"Y":111}],"AdvancedInfo":"{\"Parag\":{\"ParagNo\":6}}"},{"DetectedText":"床号:22","Confidence":99,"Polygon":[{"X":213,"Y":108},{"X":213,"Y":92},{"X":302,"Y":94},{"X":302,"Y":111}],"AdvancedInfo":"{\"Parag\":{\"ParagNo\":7}}"},{"DetectedText":"送检医师:","Confidence":99,"Polygon":[{"X":410,"Y":93},{"X":410,"Y":111},{"X":477,"Y":110},{"X":477,"Y":92}],"AdvancedInfo":"{\"Parag\":{\"ParagNo\":8}}"},{"DetectedText":"临床诊断:","Confidence":99,"Polygon":[{"X":574,"Y":112},{"X":575,"Y":94},{"X":644,"Y":96},{"X":644,"Y":113}],"AdvancedInfo":"{\"Parag\":{\"ParagNo\":9}}"},{"DetectedText":"1、1年龄:42岁","Confidence":84,"Polygon":[{"X":1,"Y":130},{"X":2,"Y":112},{"X":144,"Y":117},{"X":143,"Y":134}],"AdvancedInfo":"{\"Parag\":{\"ParagNo\":10}}"},{"DetectedText":"科别:感染性疾病科病房标本种类:血清","Confidence":98,"Polygon":[{"X":211,"Y":133},{"X":211,"Y":114},{"X":518,"Y":115},{"X":518,"Y":133}],"AdvancedInfo":"{\"Parag\":{\"ParagNo\":11}}"},{"DetectedText":"备注:","Confidence":99,"Polygon":[{"X":571,"Y":118},{"X":572,"Y":136},{"X":641,"Y":133},{"X":640,"Y":116}],"AdvancedInfo":"{\"Parag\":{\"ParagNo\":12}}"},{"DetectedText":"|处|项目","Confidence":90,"Polygon":[{"X":1,"Y":154},{"X":2,"Y":136},{"X":128,"Y":139},{"X":128,"Y":157}],"AdvancedInfo":"{\"Parag\":{\"ParagNo\":13}}"},{"DetectedText":"结果","Confidence":99,"Polygon":[{"X":209,"Y":140},{"X":209,"Y":157},{"X":243,"Y":156},{"X":243,"Y":139}],"AdvancedInfo":"{\"Parag\":{\"ParagNo\":14}}"},{"DetectedText":"参考范围单位","Confidence":99,"Polygon":[{"X":302,"Y":139},{"X":302,"Y":157},{"X":417,"Y":156},{"X":416,"Y":138}],"AdvancedInfo":"{\"Parag\":{\"ParagNo\":15}}"},{"DetectedText":"项目","Confidence":99,"Polygon":[{"X":474,"Y":138},{"X":474,"Y":157},{"X":522,"Y":156},{"X":522,"Y":137}],"AdvancedInfo":"{\"Parag\":{\"ParagNo\":16}}"},{"DetectedText":"结果参考范围单位","Confidence":99,"Polygon":[{"X":618,"Y":157},{"X":618,"Y":138},{"X":797,"Y":140},{"X":797,"Y":158}],"AdvancedInfo":"{\"Parag\":{\"ParagNo\":17}}"},{"DetectedText":"11","Confidence":80,"Polygon":[{"X":1,"Y":177},{"X":1,"Y":158},{"X":57,"Y":159},{"X":57,"Y":177}],"AdvancedInfo":"{\"Parag\":{\"ParagNo\":18}}"},{"DetectedText":"C8","Confidence":75,"Polygon":[{"X":59,"Y":177},{"X":63,"Y":166},{"X":80,"Y":172},{"X":76,"Y":183}],"AdvancedInfo":"{\"Parag\":{\"ParagNo\":18}}"},{"DetectedText":"钙","Confidence":99,"Polygon":[{"X":111,"Y":164},{"X":111,"Y":177},{"X":126,"Y":177},{"X":126,"Y":164}],"AdvancedInfo":"{\"Parag\":{\"ParagNo\":19}}"},{"DetectedText":"2.00","Confidence":99,"Polygon":[{"X":245,"Y":164},{"X":245,"Y":178},{"X":278,"Y":176},{"X":277,"Y":163}],"AdvancedInfo":"{\"Parag\":{\"ParagNo\":20}}"},{"DetectedText":"2.0--2.5  mol/LIBIL 间接胆红素","Confidence":84,"Polygon":[{"X":309,"Y":178},{"X":310,"Y":162},{"X":564,"Y":164},{"X":564,"Y":180}],"AdvancedInfo":"{\"Parag\":{\"ParagNo\":20}}"},{"DetectedText":"10.6","Confidence":99,"Polygon":[{"X":625,"Y":177},{"X":625,"Y":163},{"X":658,"Y":163},{"X":658,"Y":177}],"AdvancedInfo":"{\"Parag\":{\"ParagNo\":21}}"},{"DetectedText":"0--18","Confidence":99,"Polygon":[{"X":691,"Y":164},{"X":691,"Y":176},{"X":730,"Y":176},{"X":730,"Y":163}],"AdvancedInfo":"{\"Parag\":{\"ParagNo\":22}}"},{"DetectedText":"umol/L","Confidence":96,"Polygon":[{"X":771,"Y":165},{"X":772,"Y":179},{"X":815,"Y":176},{"X":814,"Y":161}],"AdvancedInfo":"{\"Parag\":{\"ParagNo\":23}}"},{"DetectedText":"IC02CP二氧化碳结合率25.5 20--29","Confidence":92,"Polygon":[{"X":48,"Y":185},{"X":48,"Y":203},{"X":355,"Y":200},{"X":354,"Y":182}],"AdvancedInfo":"{\"Parag\":{\"ParagNo\":24}}"},{"DetectedText":"mmo1/L|Pa前白蛋白","Confidence":96,"Polygon":[{"X":391,"Y":200},{"X":391,"Y":184},{"X":549,"Y":185},{"X":549,"Y":201}],"AdvancedInfo":"{\"Parag\":{\"ParagNo\":24}}"},{"DetectedText":"138↓180--390  mg/L","Confidence":88,"Polygon":[{"X":626,"Y":199},{"X":626,"Y":183},{"X":800,"Y":185},{"X":800,"Y":200}],"AdvancedInfo":"{\"Parag\":{\"ParagNo\":25}}"},{"DetectedText":"IAG阴离子间隙","Confidence":93,"Polygon":[{"X":48,"Y":225},{"X":48,"Y":207},{"X":182,"Y":207},{"X":182,"Y":225}],"AdvancedInfo":"{\"Parag\":{\"ParagNo\":26}}"},{"DetectedText":"10.4 8--16","Confidence":89,"Polygon":[{"X":245,"Y":207},{"X":245,"Y":223},{"X":347,"Y":223},{"X":347,"Y":207}],"AdvancedInfo":"{\"Parag\":{\"ParagNo\":27}}"},{"DetectedText":"mo1/LTP","Confidence":92,"Polygon":[{"X":390,"Y":223},{"X":390,"Y":207},{"X":458,"Y":209},{"X":458,"Y":224}],"AdvancedInfo":"{\"Parag\":{\"ParagNo\":28}}"},{"DetectedText":"总蛋白","Confidence":99,"Polygon":[{"X":490,"Y":223},{"X":491,"Y":206},{"X":535,"Y":208},{"X":535,"Y":224}],"AdvancedInfo":"{\"Parag\":{\"ParagNo\":28}}"},{"DetectedText":"56.6↓60--82  g/L","Confidence":84,"Polygon":[{"X":626,"Y":222},{"X":627,"Y":206},{"X":794,"Y":207},{"X":794,"Y":223}],"AdvancedInfo":"{\"Parag\":{\"ParagNo\":29}}"},{"DetectedText":"IBUN尿素","Confidence":91,"Polygon":[{"X":48,"Y":247},{"X":48,"Y":229},{"X":140,"Y":230},{"X":139,"Y":248}],"AdvancedInfo":"{\"Parag\":{\"ParagNo\":30}}"},{"DetectedText":"10.72 ↑2.5--6.4  mmo1/L ALB 白蛋白","Confidence":82,"Polygon":[{"X":246,"Y":244},{"X":246,"Y":228},{"X":535,"Y":231},{"X":535,"Y":247}],"AdvancedInfo":"{\"Parag\":{\"ParagNo\":31}}"},{"DetectedText":"32.1↓35--55","Confidence":99,"Polygon":[{"X":627,"Y":243},{"X":627,"Y":229},{"X":736,"Y":230},{"X":736,"Y":245}],"AdvancedInfo":"{\"Parag\":{\"ParagNo\":32}}"},{"DetectedText":"8/L","Confidence":99,"Polygon":[{"X":768,"Y":232},{"X":772,"Y":248},{"X":794,"Y":242},{"X":790,"Y":227}],"AdvancedInfo":"{\"Parag\":{\"ParagNo\":32}}"},{"DetectedText":"I|UA尿酸","Confidence":77,"Polygon":[{"X":1,"Y":267},{"X":2,"Y":250},{"X":140,"Y":252},{"X":140,"Y":269}],"AdvancedInfo":"{\"Parag\":{\"ParagNo\":33}}"},{"DetectedText":"201.53+208--428  umo1/L| GLO 球蛋白","Confidence":83,"Polygon":[{"X":246,"Y":268},{"X":246,"Y":252},{"X":536,"Y":253},{"X":536,"Y":269}],"AdvancedInfo":"{\"Parag\":{\"ParagNo\":34}}"},{"DetectedText":"24.5 20--35  g/L","Confidence":79,"Polygon":[{"X":626,"Y":251},{"X":627,"Y":268},{"X":794,"Y":268},{"X":794,"Y":251}],"AdvancedInfo":"{\"Parag\":{\"ParagNo\":35}}"},{"DetectedText":"I|Cr","Confidence":63,"Polygon":[{"X":1,"Y":288},{"X":2,"Y":269},{"X":80,"Y":276},{"X":79,"Y":294}],"AdvancedInfo":"{\"Parag\":{\"ParagNo\":36}}"},{"DetectedText":"肌酐","Confidence":99,"Polygon":[{"X":110,"Y":275},{"X":111,"Y":292},{"X":139,"Y":290},{"X":138,"Y":273}],"AdvancedInfo":"{\"Parag\":{\"ParagNo\":36}}"},{"DetectedText":"67.2 50--120  umo1/L A/G 白球比值","Confidence":79,"Polygon":[{"X":245,"Y":290},{"X":245,"Y":273},{"X":549,"Y":275},{"X":549,"Y":292}],"AdvancedInfo":"{\"Parag\":{\"ParagNo\":37}}"},{"DetectedText":"1.3","Confidence":99,"Polygon":[{"X":625,"Y":273},{"X":625,"Y":290},{"X":651,"Y":290},{"X":651,"Y":273}],"AdvancedInfo":"{\"Parag\":{\"ParagNo\":38}}"},{"DetectedText":"1.1--2.5","Confidence":99,"Polygon":[{"X":692,"Y":276},{"X":692,"Y":289},{"X":751,"Y":288},{"X":750,"Y":275}],"AdvancedInfo":"{\"Parag\":{\"ParagNo\":39}}"},{"DetectedText":"||GLU血糖","Confidence":90,"Polygon":[{"X":1,"Y":313},{"X":2,"Y":294},{"X":140,"Y":297},{"X":140,"Y":316}],"AdvancedInfo":"{\"Parag\":{\"ParagNo\":40}}"},{"DetectedText":"8.32  $ 3.8--6.1  mmo1/L TBA 总胆汁酸","Confidence":74,"Polygon":[{"X":245,"Y":312},{"X":245,"Y":295},{"X":548,"Y":297},{"X":548,"Y":314}],"AdvancedInfo":"{\"Parag\":{\"ParagNo\":41}}"},{"DetectedText":"6.5","Confidence":99,"Polygon":[{"X":625,"Y":311},{"X":625,"Y":295},{"X":651,"Y":296},{"X":651,"Y":311}],"AdvancedInfo":"{\"Parag\":{\"ParagNo\":42}}"},{"DetectedText":"0--10","Confidence":99,"Polygon":[{"X":691,"Y":311},{"X":691,"Y":297},{"X":730,"Y":298},{"X":730,"Y":311}],"AdvancedInfo":"{\"Parag\":{\"ParagNo\":43}}"},{"DetectedText":"umol/L","Confidence":96,"Polygon":[{"X":771,"Y":298},{"X":772,"Y":313},{"X":815,"Y":310},{"X":814,"Y":296}],"AdvancedInfo":"{\"Parag\":{\"ParagNo\":44}}"},{"DetectedText":"||GSP糖化血清蛋白","Confidence":88,"Polygon":[{"X":1,"Y":336},{"X":2,"Y":317},{"X":196,"Y":319},{"X":196,"Y":338}],"AdvancedInfo":"{\"Parag\":{\"ParagNo\":45}}"},{"DetectedText":"1.57 1.40--2.50 mmo1/L| CHOL 总胆固醇","Confidence":83,"Polygon":[{"X":246,"Y":336},{"X":246,"Y":319},{"X":548,"Y":320},{"X":548,"Y":337}],"AdvancedInfo":"{\"Parag\":{\"ParagNo\":46}}"},{"DetectedText":"2.43 ↓3.1--6.0  mmo1/L","Confidence":80,"Polygon":[{"X":625,"Y":335},{"X":625,"Y":318},{"X":815,"Y":319},{"X":815,"Y":336}],"AdvancedInfo":"{\"Parag\":{\"ParagNo\":47}}"},{"DetectedText":"I|ALT谷丙转氨酶","Confidence":87,"Polygon":[{"X":1,"Y":357},{"X":1,"Y":339},{"X":182,"Y":341},{"X":182,"Y":360}],"AdvancedInfo":"{\"Parag\":{\"ParagNo\":48}}"},{"DetectedText":"223↑0--40","Confidence":99,"Polygon":[{"X":245,"Y":356},{"X":245,"Y":339},{"X":347,"Y":341},{"X":347,"Y":358}],"AdvancedInfo":"{\"Parag\":{\"ParagNo\":49}}"},{"DetectedText":"U/LTG甘油三脂","Confidence":99,"Polygon":[{"X":388,"Y":358},{"X":389,"Y":340},{"X":550,"Y":341},{"X":550,"Y":359}],"AdvancedInfo":"{\"Parag\":{\"ParagNo\":50}}"},{"DetectedText":"0.91  0.48--1.88 mmo1/L","Confidence":83,"Polygon":[{"X":626,"Y":356},{"X":626,"Y":341},{"X":814,"Y":342},{"X":814,"Y":357}],"AdvancedInfo":"{\"Parag\":{\"ParagNo\":51}}"},{"DetectedText":"I|AST谷草转氨酶","Confidence":86,"Polygon":[{"X":2,"Y":381},{"X":2,"Y":363},{"X":182,"Y":364},{"X":182,"Y":382}],"AdvancedInfo":"{\"Parag\":{\"ParagNo\":52}}"},{"DetectedText":"82↑0--40","Confidence":99,"Polygon":[{"X":245,"Y":379},{"X":245,"Y":362},{"X":348,"Y":363},{"X":348,"Y":379}],"AdvancedInfo":"{\"Parag\":{\"ParagNo\":53}}"},{"DetectedText":"U/LHDL-C高密度脂蛋白胆固醇0.88","Confidence":98,"Polygon":[{"X":388,"Y":365},{"X":389,"Y":382},{"X":658,"Y":380},{"X":658,"Y":364}],"AdvancedInfo":"{\"Parag\":{\"ParagNo\":54}}"},{"DetectedText":"0.74--2.04 mmo1/L","Confidence":92,"Polygon":[{"X":691,"Y":365},{"X":691,"Y":378},{"X":814,"Y":378},{"X":814,"Y":365}],"AdvancedInfo":"{\"Parag\":{\"ParagNo\":55}}"},{"DetectedText":"I|s/L谷草/谷丙","Confidence":89,"Polygon":[{"X":1,"Y":403},{"X":1,"Y":385},{"X":175,"Y":386},{"X":175,"Y":405}],"AdvancedInfo":"{\"Parag\":{\"ParagNo\":56}}"},{"DetectedText":"0.4↓0.8--1.5","Confidence":98,"Polygon":[{"X":245,"Y":402},{"X":246,"Y":385},{"X":369,"Y":386},{"X":369,"Y":403}],"AdvancedInfo":"{\"Parag\":{\"ParagNo\":57}}"},{"DetectedText":"LDL-C低密度脂蛋白胆固醇0.87↓2.27--3.62 mmol/L","Confidence":95,"Polygon":[{"X":441,"Y":388},{"X":441,"Y":404},{"X":814,"Y":402},{"X":814,"Y":386}],"AdvancedInfo":"{\"Parag\":{\"ParagNo\":58}}"},{"DetectedText":"||ALP碱性磷酸酶","Confidence":92,"Polygon":[{"X":1,"Y":426},{"X":1,"Y":407},{"X":181,"Y":408},{"X":181,"Y":427}],"AdvancedInfo":"{\"Parag\":{\"ParagNo\":59}}"},{"DetectedText":"63","Confidence":99,"Polygon":[{"X":244,"Y":410},{"X":245,"Y":424},{"X":263,"Y":423},{"X":262,"Y":408}],"AdvancedInfo":"{\"Parag\":{\"ParagNo\":60}}"},{"DetectedText":"30--120U/L VLDL-C极低密度脂蛋白胆固0.18","Confidence":94,"Polygon":[{"X":311,"Y":426},{"X":311,"Y":409},{"X":658,"Y":409},{"X":658,"Y":426}],"AdvancedInfo":"{\"Parag\":{\"ParagNo\":61}}"},{"DetectedText":"0--0.58","Confidence":99,"Polygon":[{"X":691,"Y":410},{"X":691,"Y":423},{"X":743,"Y":423},{"X":743,"Y":410}],"AdvancedInfo":"{\"Parag\":{\"ParagNo\":62}}"},{"DetectedText":"mmol/L","Confidence":94,"Polygon":[{"X":769,"Y":412},{"X":770,"Y":426},{"X":815,"Y":423},{"X":814,"Y":408}],"AdvancedInfo":"{\"Parag\":{\"ParagNo\":62}}"},{"DetectedText":"I IGGTY谷氨酰转肽酶320↑0--50","Confidence":88,"Polygon":[{"X":1,"Y":430},{"X":1,"Y":450},{"X":346,"Y":448},{"X":346,"Y":429}],"AdvancedInfo":"{\"Parag\":{\"ParagNo\":63}}"},{"DetectedText":"U/LAPOA1载脂蛋白A1","Confidence":93,"Polygon":[{"X":389,"Y":448},{"X":389,"Y":432},{"X":562,"Y":432},{"X":562,"Y":449}],"AdvancedInfo":"{\"Parag\":{\"ParagNo\":64}}"},{"DetectedText":"0.79↓1.20--1.76 g/L","Confidence":91,"Polygon":[{"X":627,"Y":447},{"X":627,"Y":431},{"X":794,"Y":431},{"X":794,"Y":448}],"AdvancedInfo":"{\"Parag\":{\"ParagNo\":65}}"},{"DetectedText":"1 |CHE胆碱脂酶","Confidence":72,"Polygon":[{"X":1,"Y":470},{"X":1,"Y":451},{"X":168,"Y":454},{"X":168,"Y":473}],"AdvancedInfo":"{\"Parag\":{\"ParagNo\":66}}"},{"DetectedText":"3538↓4000--13000U/L APOB 载脂蛋白B","Confidence":91,"Polygon":[{"X":246,"Y":468},{"X":246,"Y":452},{"X":557,"Y":455},{"X":557,"Y":471}],"AdvancedInfo":"{\"Parag\":{\"ParagNo\":67}}"},{"DetectedText":"0.28 ↓0.63--1.14 8/L","Confidence":85,"Polygon":[{"X":625,"Y":468},{"X":625,"Y":453},{"X":794,"Y":454},{"X":794,"Y":469}],"AdvancedInfo":"{\"Parag\":{\"ParagNo\":68}}"},{"DetectedText":"||ADA腺苷脱氨酶","Confidence":87,"Polygon":[{"X":1,"Y":493},{"X":2,"Y":475},{"X":182,"Y":477},{"X":182,"Y":494}],"AdvancedInfo":"{\"Parag\":{\"ParagNo\":69}}"},{"DetectedText":"15","Confidence":99,"Polygon":[{"X":245,"Y":491},{"X":245,"Y":475},{"X":263,"Y":475},{"X":263,"Y":491}],"AdvancedInfo":"{\"Parag\":{\"ParagNo\":70}}"},{"DetectedText":"0--15","Confidence":99,"Polygon":[{"X":310,"Y":490},{"X":310,"Y":477},{"X":349,"Y":477},{"X":348,"Y":490}],"AdvancedInfo":"{\"Parag\":{\"ParagNo\":71}}"},{"DetectedText":"U/LAMY淀粉酶","Confidence":96,"Polygon":[{"X":389,"Y":493},{"X":389,"Y":477},{"X":535,"Y":478},{"X":535,"Y":494}],"AdvancedInfo":"{\"Parag\":{\"ParagNo\":72}}"},{"DetectedText":"39","Confidence":99,"Polygon":[{"X":626,"Y":476},{"X":627,"Y":491},{"X":642,"Y":490},{"X":641,"Y":476}],"AdvancedInfo":"{\"Parag\":{\"ParagNo\":73}}"},{"DetectedText":"0--140  U/L","Confidence":81,"Polygon":[{"X":691,"Y":476},{"X":691,"Y":492},{"X":793,"Y":491},{"X":793,"Y":476}],"AdvancedInfo":"{\"Parag\":{\"ParagNo\":74}}"},{"DetectedText":"I TBIL总胆红素","Confidence":83,"Polygon":[{"X":1,"Y":514},{"X":1,"Y":496},{"X":168,"Y":499},{"X":168,"Y":517}],"AdvancedInfo":"{\"Parag\":{\"ParagNo\":75}}"},{"DetectedText":"17.0 5--21","Confidence":89,"Polygon":[{"X":245,"Y":514},{"X":245,"Y":499},{"X":348,"Y":499},{"X":348,"Y":515}],"AdvancedInfo":"{\"Parag\":{\"ParagNo\":76}}"},{"DetectedText":"umol/LLPS脂肪酶","Confidence":92,"Polygon":[{"X":390,"Y":497},{"X":390,"Y":517},{"X":534,"Y":517},{"X":534,"Y":497}],"AdvancedInfo":"{\"Parag\":{\"ParagNo\":77}}"},{"DetectedText":"33","Confidence":99,"Polygon":[{"X":626,"Y":514},{"X":626,"Y":500},{"X":643,"Y":500},{"X":643,"Y":514}],"AdvancedInfo":"{\"Parag\":{\"ParagNo\":78}}"},{"DetectedText":"0--60","Confidence":99,"Polygon":[{"X":691,"Y":512},{"X":691,"Y":500},{"X":729,"Y":500},{"X":728,"Y":512}],"AdvancedInfo":"{\"Parag\":{\"ParagNo\":79}}"},{"DetectedText":"U/L","Confidence":99,"Polygon":[{"X":770,"Y":513},{"X":770,"Y":499},{"X":793,"Y":499},{"X":793,"Y":513}],"AdvancedInfo":"{\"Parag\":{\"ParagNo\":80}}"},{"DetectedText":"IDBIL直接胆红素","Confidence":92,"Polygon":[{"X":48,"Y":521},{"X":48,"Y":538},{"X":182,"Y":538},{"X":182,"Y":521}],"AdvancedInfo":"{\"Parag\":{\"ParagNo\":81}}"},{"DetectedText":"6.4↑0--3.4","Confidence":97,"Polygon":[{"X":246,"Y":535},{"X":246,"Y":521},{"X":356,"Y":521},{"X":356,"Y":535}],"AdvancedInfo":"{\"Parag\":{\"ParagNo\":82}}"},{"DetectedText":"umo1/LIgA免疫球蛋白A","Confidence":98,"Polygon":[{"X":393,"Y":537},{"X":393,"Y":521},{"X":571,"Y":522},{"X":571,"Y":538}],"AdvancedInfo":"{\"Parag\":{\"ParagNo\":83}}"},{"DetectedText":"3.51  t 2.01--2.69 g/L","Confidence":79,"Polygon":[{"X":625,"Y":535},{"X":625,"Y":520},{"X":794,"Y":522},{"X":794,"Y":536}],"AdvancedInfo":"{\"Parag\":{\"ParagNo\":84}}"},{"DetectedText":"检验时间2018/11/23 9:30","Confidence":94,"Polygon":[{"X":62,"Y":563},{"X":62,"Y":546},{"X":247,"Y":546},{"X":247,"Y":563}],"AdvancedInfo":"{\"Parag\":{\"ParagNo\":85}}"},{"DetectedText":"报告时间:2018/11/2310:05检验者","Confidence":99,"Polygon":[{"X":301,"Y":563},{"X":301,"Y":546},{"X":552,"Y":547},{"X":552,"Y":564}],"AdvancedInfo":"{\"Parag\":{\"ParagNo\":86}}"},{"DetectedText":"审","Confidence":90,"Polygon":[{"X":677,"Y":549},{"X":677,"Y":564},{"X":695,"Y":564},{"X":695,"Y":549}],"AdvancedInfo":"{\"Parag\":{\"ParagNo\":87}}"},{"DetectedText":"此结果仅对该标本负责，如有疑问请于24小时内与实验室联系，0372-3124131","Confidence":99,"Polygon":[{"X":61,"Y":585},{"X":61,"Y":568},{"X":592,"Y":569},{"X":592,"Y":586}],"AdvancedInfo":"{\"Parag\":{\"ParagNo\":88}}"}],"RequestId":"a8d64510-9f23-4140-8253-69ba5a224d5c"}
